pulse2/__init__.py
pulse2/active_model.py
pulse2/active_stress.py
pulse2/boundary_conditions.py
pulse2/cardiac_model.py
pulse2/compressibility.py
pulse2/config.py
pulse2/exceptions.py
pulse2/functions.py
pulse2/geometry.py
pulse2/holzapfelogden.py
pulse2/invariants.py
pulse2/itertarget.py
pulse2/kinematics.py
pulse2/linear_elastic.py
pulse2/material_model.py
pulse2/problem.py
pulse2/solver.py
fenics_pulse2-0.1.1.dist-info/LICENSE
fenics_pulse2-0.1.1.dist-info/METADATA
fenics_pulse2-0.1.1.dist-info/WHEEL
fenics_pulse2-0.1.1.dist-info/top_level.txt
fenics_pulse2-0.1.1.dist-info/RECORD
