Metadata-Version: 2.1
Name: fenics-pulse2
Version: 0.1.1
Summary: Cardiac Mechanics simulator
Author-email: Henrik Finsberg <henriknf@simula.no>
License: Copyright 2023 Henrik Finsberg
Project-URL: Homepage, https://finsberg.github.io/pulse2
Project-URL: Documentation, https://finsberg.github.io/pulse2
Project-URL: Source, https://github.com/finsberg/pulse2
Project-URL: Tracker, https://github.com/finsberg/pulse2/issues
Keywords: cardiac,mechanics,closed loop
Requires-Python: >=3.10
License-File: LICENSE
Requires-Dist: numpy
Requires-Dist: scipy
Requires-Dist: tqdm
Requires-Dist: typing-extensions
Provides-Extra: all
Requires-Dist: fenics-pulse2[test] ; extra == 'all'
Requires-Dist: fenics-pulse2[docs] ; extra == 'all'
Requires-Dist: fenics-pulse2[pypi] ; extra == 'all'
Requires-Dist: fenics-pulse2[demo] ; extra == 'all'
Requires-Dist: fenics-pulse2[dev] ; extra == 'all'
Provides-Extra: demo
Requires-Dist: cardiac-geometries ; extra == 'demo'
Requires-Dist: ldrb ; extra == 'demo'
Provides-Extra: dev
Requires-Dist: pdbpp ; extra == 'dev'
Requires-Dist: ipython ; extra == 'dev'
Requires-Dist: bump-my-version ; extra == 'dev'
Requires-Dist: pre-commit ; extra == 'dev'
Provides-Extra: docs
Requires-Dist: jupyter-book ; extra == 'docs'
Requires-Dist: jupytext ; extra == 'docs'
Requires-Dist: fenics-pulse2[demo] ; extra == 'docs'
Provides-Extra: pypi
Requires-Dist: twine ; extra == 'pypi'
Requires-Dist: build ; extra == 'pypi'
Provides-Extra: test
Requires-Dist: pytest ; extra == 'test'
Requires-Dist: pytest-cov ; extra == 'test'
Requires-Dist: cardiac-geometries ; extra == 'test'
